[
  {
    "elementType": "labels",
    "stylers": [
      {
        "gamma": 0.56
      }
    ]
  },
  {
    "featureType": "administrative.locality",
    "elementType": "labels",
    "stylers": [
      {
        "lightness": 25
      }
    ]
  },
  {
    "featureType": "landscape.man_made",
    "stylers": [
      {
        "weight": 0.5
      }
    ]
  },
  {
    "featureType": "landscape.man_made",
    "elementType": "geometry.fill",
    "stylers": [
      {
        "color": "#7f7f7f"
      },
      {
        "lightness": 15
      }
    ]
  },
  {
    "featureType": "landscape.man_made",
    "elementType": "geometry.stroke",
    "stylers": [
      {
        "color": "#565949"
      },
      {
        "visibility": "on"
      },
      {
        "weight": 0.5
      }
    ]
  },
  {
    "featureType": "landscape.natural",
    "elementType": "geometry.fill",
    "stylers": [
      {
        "color": "#89dd35"
      },
      {
        "saturation": -35
      },
      {
        "lightness": 15
      }
    ]
  },
  {
    "featureType": "poi",
    "elementType": "geometry.fill",
    "stylers": [
      {
        "color": "#8fe449"
      },
      {
        "saturation": -35
      },
      {
        "lightness": 15
      },
      {
        "visibility": "on"
      }
    ]
  },
  {
    "featureType": "poi.business",
    "stylers": [
      {
        "saturation": 70
      },
      {
        "lightness": -60
      },
      {
        "visibility": "off"
      }
    ]
  },
  {
    "featureType": "poi.government",
    "stylers": [
      {
        "visibility": "off"
      }
    ]
  },
  {
    "featureType": "poi.school",
    "elementType": "geometry.fill",
    "stylers": [
      {
        "color": "#c0c0af"
      }
    ]
  },
  {
    "featureType": "poi.school",
    "elementType": "labels",
    "stylers": [
      {
        "weight": 4
      }
    ]
  },
  {
    "featureType": "road.arterial",
    "elementType": "geometry.fill",
    "stylers": [
      {
        "color": "#e3e3d7"
      }
    ]
  },
  {
    "featureType": "road.arterial",
    "elementType": "labels",
    "stylers": [
      {
        "lightness": 45
      }
    ]
  },
  {
    "featureType": "road.highway",
    "elementType": "geometry",
    "stylers": [
      {
        "color": "#fde471"
      }
    ]
  },
  {
    "featureType": "road.highway",
    "elementType": "labels",
    "stylers": [
      {
        "lightness": 45
      }
    ]
  },
  {
    "featureType": "road.local",
    "elementType": "geometry.fill",
    "stylers": [
      {
        "color": "#ddddd2"
      },
      {
        "weight": 0.5
      }
    ]
  },
  {
    "featureType": "water",
    "elementType": "geometry.fill",
    "stylers": [
      {
        "lightness": -30
      },
      {
        "gamma": 3.16
      }
    ]
  },
  {
    "featureType": "water",
    "elementType": "labels.text.fill",
    "stylers": [
      {
        "color": "#1c4fb0"
      }
    ]
  }
]